{
    "apps": [
        {
            "name": "AddApp",
            "image": "./Assets/Images/netflix.jpg",
            "cmd": "librewolf"
        },
        {
            "name": "funtogo",
            "image": "./Assets/Images/addApp.png",
            "cmd": "echo 'fun'"
        },
        {
            "name": "funtogo2",
            "image": "./Assets/Images/addApp.png",
            "cmd": "echo 'fun'"
        },
        {
            "name": "funtogo3",
            "image": "./Assets/Images/addApp.png",
            "cmd": "echo 'fun'"
        }
    ],
    "Settings": [
        {
            "name": "defaultApp",
            "image": "./Assets/Images/addApp.png",
            "cmd": "echo 'fun'"
        },
        {
            "name": "funtogo3",
            "image": "./Assets/Images/addApp.png",
            "cmd": "echo 'fun'"
        },
        {
            "name": "funtogo2",
            "image": "./Assets/Images/addApp.png",
            "cmd": "echo 'fun'"
        }
    ]

}
